catbook/__init__.py
catbook/book.py
catbook/book_metadata.py
catbook/builder.py
catbook/files.py
catbook/fonts.py
catbook/markup.py
catbook/metadata.py
catbook/metadata_section.py
catbook/misc.py
catbook/regular_section.py
catbook/section.py
catbook/section_metadata.py
catbook/tokenizer.py
catbook-0.1.1.3.dist-info/LICENSE
catbook-0.1.1.3.dist-info/METADATA
catbook-0.1.1.3.dist-info/WHEEL
catbook-0.1.1.3.dist-info/RECORD
