Metadata-Version: 2.1
Name: catbook
Version: 0.1.1.3
Summary: A library for compiling text files into a book-form docx file
Author: David Kershaw
Author-email: dk107dk@hotmail.com
Requires-Python: >=3.12,<4.0
Classifier: Environment :: Console
Classifier: Programming Language :: Python :: 3
Classifier: Programming Language :: Python :: 3.12
Classifier: Topic :: Documentation
Classifier: Topic :: Printing
Classifier: Topic :: Text Processing :: Markup
Requires-Dist: docxcompose (>=1.4.0,<2.0.0)
Requires-Dist: python-docx (>=1.1.0,<2.0.0)
Project-URL: Github, https://github.com/dk107dk/catbook
